{
  "TotalRecords": 75,
  "Players": [
    {
      "Joueur": "[S.P.Q.R] Johnny Guitouze",
      "Image": null,
      "Twitch": null,
      "Youtube": null,
      "Couleur": "Gris"
    },
    {
      "Joueur": "Acuado",
      "Image": null,
      "Twitch": null,
      "Youtube": null,
      "Couleur": "Turquoise"
    },
    {
      "Joueur": "Akunoto",
      "Image": null,
      "Twitch": null,
      "Youtube": null,
      "Couleur": "Orange"
    },
    {
      "Joueur": "alexisyohann321",
      "Image": null,
      "Twitch": null,
      "Youtube": null,
      "Couleur": "Jaune"
    },
    {
      "Joueur": "angedudestin",
      "Image": null,
      "Twitch": null,
      "Youtube": null,
      "Couleur": "Gris"
    },
    {
      "Joueur": "AshimaOSirena",
      "Image": null,
      "Twitch": null,
      "Youtube": null,
      "Couleur": "Marron"
    },
    {
      "Joueur": "Baout",
      "Image": null,
      "Twitch": null,
      "Youtube": null,
      "Couleur": "Rose"
    },
    {
      "Joueur": "Batou",
      "Image": null,
      "Twitch": null,
      "Youtube": null,
      "Couleur": "Jaune"
    },
    {
      "Joueur": "bluenovae",
      "Image": null,
      "Twitch": null,
      "Youtube": null,
      "Couleur": "Vert foncé"
    },
    {
      "Joueur": "Brybry",
      "Image": null,
      "Twitch": null,
      "Youtube": null,
      "Couleur": "Vert foncé"
    },
    {
      "Joueur": "Bytell",
      "Image": null,
      "Twitch": null,
      "Youtube": null,
      "Couleur": "Vert pomme"
    },
    {
      "Joueur": "Cachou",
      "Image": null,
      "Twitch": null,
      "Youtube": null,
      "Couleur": "Rouge"
    },
    {
      "Joueur": "Carococo",
      "Image": null,
      "Twitch": null,
      "Youtube": null,
      "Couleur": "Orange"
    },
    {
      "Joueur": "CHLOE",
      "Image": null,
      "Twitch": null,
      "Youtube": null,
      "Couleur": "Turquoise"
    },
    {
      "Joueur": "ClydeCreator",
      "Image": null,
      "Twitch": null,
      "Youtube": null,
      "Couleur": "Rouge"
    },
    {
      "Joueur": "Davimithryl",
      "Image": null,
      "Twitch": null,
      "Youtube": null,
      "Couleur": "Bleu royal"
    },
    {
      "Joueur": "Dianibal",
      "Image": null,
      "Twitch": null,
      "Youtube": null,
      "Couleur": "Vert foncé"
    },
    {
      "Joueur": "Edestion",
      "Image": null,
      "Twitch": null,
      "Youtube": null,
      "Couleur": "Orange"
    },
    {
      "Joueur": "Edjadada",
      "Image": null,
      "Twitch": null,
      "Youtube": null,
      "Couleur": "Rose"
    },
    {
      "Joueur": "Ekaenerys",
      "Image": null,
      "Twitch": null,
      "Youtube": null,
      "Couleur": "Jaune"
    },
    {
      "Joueur": "Enamore",
      "Image": null,
      "Twitch": null,
      "Youtube": null,
      "Couleur": "Jaune"
    },
    {
      "Joueur": "Flonflon",
      "Image": null,
      "Twitch": null,
      "Youtube": null,
      "Couleur": "Vert pomme"
    },
    {
      "Joueur": "Foiegrette",
      "Image": null,
      "Twitch": null,
      "Youtube": null,
      "Couleur": "Violet"
    },
    {
      "Joueur": "Gaëtan R",
      "Image": null,
      "Twitch": null,
      "Youtube": null,
      "Couleur": "Bleu foncé"
    },
    {
      "Joueur": "Garrus / Villentretenmerth",
      "Image": null,
      "Twitch": null,
      "Youtube": null,
      "Couleur": "Bleu royal"
    },
    {
      "Joueur": "Gom4rt",
      "Image": null,
      "Twitch": null,
      "Youtube": null,
      "Couleur": "Rouge"
    },
    {
      "Joueur": "IAmLittleSunn",
      "Image": null,
      "Twitch": null,
      "Youtube": null,
      "Couleur": "Orange"
    },
    {
      "Joueur": "Jahad",
      "Image": null,
      "Twitch": null,
      "Youtube": null,
      "Couleur": "Bleu royal"
    },
    {
      "Joueur": "Johnny",
      "Image": null,
      "Twitch": null,
      "Youtube": null,
      "Couleur": "Gris"
    },
    {
      "Joueur": "Julard",
      "Image": null,
      "Twitch": null,
      "Youtube": null,
      "Couleur": "Vert pomme"
    },
    {
      "Joueur": "khalen",
      "Image": null,
      "Twitch": null,
      "Youtube": null,
      "Couleur": "Bleu royal"
    },
    {
      "Joueur": "Kid",
      "Image": null,
      "Twitch": null,
      "Youtube": null,
      "Couleur": "Marron"
    },
    {
      "Joueur": "Kitsulia",
      "Image": null,
      "Twitch": null,
      "Youtube": null,
      "Couleur": "Gris"
    },
    {
      "Joueur": "Kyria",
      "Image": null,
      "Twitch": null,
      "Youtube": null,
      "Couleur": "Violet"
    },
    {
      "Joueur": "Laulah",
      "Image": null,
      "Twitch": null,
      "Youtube": null,
      "Couleur": "Rouge"
    },
    {
      "Joueur": "Lhuun",
      "Image": null,
      "Twitch": null,
      "Youtube": null,
      "Couleur": "Marron"
    },
    {
      "Joueur": "Luluxurious",
      "Image": null,
      "Twitch": null,
      "Youtube": null,
      "Couleur": "Jaune"
    },
    {
      "Joueur": "lunix",
      "Image": null,
      "Twitch": null,
      "Youtube": null,
      "Couleur": "Vert foncé"
    },
    {
      "Joueur": "LuttiLutti",
      "Image": null,
      "Twitch": null,
      "Youtube": null,
      "Couleur": "Orange"
    },
    {
      "Joueur": "Major-049",
      "Image": null,
      "Twitch": null,
      "Youtube": null,
      "Couleur": "Turquoise"
    },
    {
      "Joueur": "MaMaPaprika",
      "Image": null,
      "Twitch": null,
      "Youtube": null,
      "Couleur": "Orange"
    },
    {
      "Joueur": "mars.healus",
      "Image": null,
      "Twitch": null,
      "Youtube": null,
      "Couleur": "Rose"
    },
    {
      "Joueur": "Mathy",
      "Image": null,
      "Twitch": null,
      "Youtube": null,
      "Couleur": "Jaune"
    },
    {
      "Joueur": "Meyame ( Hisae )",
      "Image": null,
      "Twitch": null,
      "Youtube": null,
      "Couleur": "Rouge"
    },
    {
      "Joueur": "Mickalow",
      "Image": null,
      "Twitch": null,
      "Youtube": null,
      "Couleur": "Violet"
    },
    {
      "Joueur": "Monodie",
      "Image": null,
      "Twitch": null,
      "Youtube": null,
      "Couleur": "Bleu foncé"
    },
    {
      "Joueur": "Moonkey",
      "Image": null,
      "Twitch": null,
      "Youtube": null,
      "Couleur": "Rouge"
    },
    {
      "Joueur": "Mysa",
      "Image": null,
      "Twitch": null,
      "Youtube": null,
      "Couleur": "Violet"
    },
    {
      "Joueur": "Mystique",
      "Image": null,
      "Twitch": null,
      "Youtube": null,
      "Couleur": "Rouge"
    },
    {
      "Joueur": "Nakilyu",
      "Image": null,
      "Twitch": null,
      "Youtube": null,
      "Couleur": "Vert pomme"
    },
    {
      "Joueur": "Nales",
      "Image": null,
      "Twitch": null,
      "Youtube": null,
      "Couleur": "Bleu foncé"
    },
    {
      "Joueur": "Neagari",
      "Image": null,
      "Twitch": null,
      "Youtube": null,
      "Couleur": "Marron"
    },
    {
      "Joueur": "Nocxy",
      "Image": null,
      "Twitch": null,
      "Youtube": null,
      "Couleur": "Vert pomme"
    },
    {
      "Joueur": "Ponce",
      "Image": null,
      "Twitch": null,
      "Youtube": null,
      "Couleur": "Bleu foncé"
    },
    {
      "Joueur": "potedeo",
      "Image": null,
      "Twitch": null,
      "Youtube": null,
      "Couleur": "Gris"
    },
    {
      "Joueur": "QuicheLoLardon",
      "Image": null,
      "Twitch": null,
      "Youtube": null,
      "Couleur": "Orange"
    },
    {
      "Joueur": "Raumane",
      "Image": null,
      "Twitch": null,
      "Youtube": null,
      "Couleur": "Marron"
    },
    {
      "Joueur": "RessaPanda",
      "Image": null,
      "Twitch": null,
      "Youtube": null,
      "Couleur": "Orange"
    },
    {
      "Joueur": "RomainJacques",
      "Image": null,
      "Twitch": null,
      "Youtube": null,
      "Couleur": "Jaune"
    },
    {
      "Joueur": "Sekanor",
      "Image": null,
      "Twitch": null,
      "Youtube": null,
      "Couleur": "Vert foncé"
    },
    {
      "Joueur": "Sonnette",
      "Image": null,
      "Twitch": null,
      "Youtube": null,
      "Couleur": "Rose"
    },
    {
      "Joueur": "Stalbadass",
      "Image": null,
      "Twitch": null,
      "Youtube": null,
      "Couleur": "Vert pomme"
    },
    {
      "Joueur": "Staro",
      "Image": null,
      "Twitch": null,
      "Youtube": null,
      "Couleur": "Bleu royal"
    },
    {
      "Joueur": "Timaki",
      "Image": null,
      "Twitch": null,
      "Youtube": null,
      "Couleur": "Vert foncé"
    },
    {
      "Joueur": "TL areliaNNNN",
      "Image": null,
      "Twitch": null,
      "Youtube": null,
      "Couleur": "Bleu royal"
    },
    {
      "Joueur": "Tomill",
      "Image": null,
      "Twitch": null,
      "Youtube": null,
      "Couleur": "Violet"
    },
    {
      "Joueur": "Tovi",
      "Image": null,
      "Twitch": null,
      "Youtube": null,
      "Couleur": "Gris"
    },
    {
      "Joueur": "Tsuna",
      "Image": null,
      "Twitch": null,
      "Youtube": null,
      "Couleur": "Marron"
    },
    {
      "Joueur": "TTanjun",
      "Image": null,
      "Twitch": null,
      "Youtube": null,
      "Couleur": "Vert pomme"
    },
    {
      "Joueur": "twitch.tv/hornicoo",
      "Image": null,
      "Twitch": null,
      "Youtube": null,
      "Couleur": "Rouge"
    },
    {
      "Joueur": "VVentus02",
      "Image": null,
      "Twitch": null,
      "Youtube": null,
      "Couleur": "Turquoise"
    },
    {
      "Joueur": "Yoshikuri",
      "Image": null,
      "Twitch": null,
      "Youtube": null,
      "Couleur": "Vert pomme"
    },
    {
      "Joueur": "YUKARI",
      "Image": null,
      "Twitch": null,
      "Youtube": null,
      "Couleur": "Violet"
    },
    {
      "Joueur": "Zest",
      "Image": null,
      "Twitch": null,
      "Youtube": null,
      "Couleur": "Jaune"
    },
    {
      "Joueur": "Βακυrα",
      "Image": null,
      "Twitch": null,
      "Youtube": null,
      "Couleur": "Marron"
    }
  ],
  "description": "Player data extracted from Discord Team game logs. Social media links not available."
}